{
  "compilerOptions": {
    "lib": [
      "ESNext"
    ],
    "target": "ESNext",
    "module": "ESNext",
    "moduleResolution": "bundler",
    "moduleDetection": "force",
    "noEmit": true,
    "allowJs": true,
    "checkJs": true,
    "resolveJsonModule": true,
    "allowImportingTsExtensions": true,
    "allowSyntheticDefaultImports": true,
    "strict": true,
    "allowUnreachableCode": false,
    "allowUnusedLabels": false,
    "noFallthroughCasesInSwitch": true,
    "noImplicitOverride": true,
    "noImplicitReturns": true,
    "noUncheckedIndexedAccess": true,
    "noUnusedLocals": true,
    "noUnusedParameters": true,
    "noUncheckedSideEffectImports": true,
    "removeComments": true,
    "verbatimModuleSyntax": true,
    "skipLibCheck": true
  }
}
